nat/meta/pypi.md
nat/plugins/customizer/__init__.py
nat/plugins/customizer/register.py
nat/plugins/customizer/dpo/__init__.py
nat/plugins/customizer/dpo/config.py
nat/plugins/customizer/dpo/register.py
nat/plugins/customizer/dpo/trainer.py
nat/plugins/customizer/dpo/trainer_adapter.py
nat/plugins/customizer/dpo/trajectory_builder.py
nvidia_nat_nemo_customizer-1.5.0a20260130.dist-info/licenses/LICENSE-3rd-party.txt
nvidia_nat_nemo_customizer-1.5.0a20260130.dist-info/licenses/LICENSE.md
nvidia_nat_nemo_customizer-1.5.0a20260130.dist-info/METADATA
nvidia_nat_nemo_customizer-1.5.0a20260130.dist-info/WHEEL
nvidia_nat_nemo_customizer-1.5.0a20260130.dist-info/entry_points.txt
nvidia_nat_nemo_customizer-1.5.0a20260130.dist-info/top_level.txt
nvidia_nat_nemo_customizer-1.5.0a20260130.dist-info/RECORD
